django_activity_tracker/__init__.py
django_activity_tracker/admin.py
django_activity_tracker/apps.py
django_activity_tracker/models.py
django_activity_tracker/serializers.py
django_activity_tracker/urls.py
django_activity_tracker/views.py
django_activity_tracker-1.0.1.dist-info/LICENSE
django_activity_tracker-1.0.1.dist-info/METADATA
django_activity_tracker-1.0.1.dist-info/WHEEL
django_activity_tracker-1.0.1.dist-info/RECORD
